availsim4-2.2.1.dist-info/licenses/AUTHORS
availsim4-2.2.1.dist-info/licenses/LICENSE
availsim4core/__init__.py
availsim4core/configuration.py
availsim4core/main.py
availsim4core/logging/logging.conf
availsim4core/resources/__init__.py
availsim4core/resources/excel_strings.py
availsim4core/resources/script_templates/__init__.py
availsim4core/resources/script_templates/master_job_template.sh
availsim4core/resources/script_templates/master_submission_template.sub
availsim4core/resources/script_templates/single_job_template.sh
availsim4core/resources/script_templates/single_submission_template.sub
availsim4core/src/__init__.py
availsim4core/src/analysis.py
availsim4core/src/context/__init__.py
availsim4core/src/context/context.py
availsim4core/src/context/phase/__init__.py
availsim4core/src/context/phase/phase.py
availsim4core/src/context/phase/phase_manager.py
availsim4core/src/context/rca/__init__.py
availsim4core/src/context/rca/rca_manager.py
availsim4core/src/context/rca/rca_record.py
availsim4core/src/context/system/__init__.py
availsim4core/src/context/system/architecture_entry.py
availsim4core/src/context/system/failure.py
availsim4core/src/context/system/failure_factory.py
availsim4core/src/context/system/failure_mode.py
availsim4core/src/context/system/failure_mode_assignments.py
availsim4core/src/context/system/inspection.py
availsim4core/src/context/system/minimal_replaceable_unit.py
availsim4core/src/context/system/phase_jump_trigger.py
availsim4core/src/context/system/rca_trigger.py
availsim4core/src/context/system/sanity_check.py
availsim4core/src/context/system/system_element.py
availsim4core/src/context/system/system_template.py
availsim4core/src/context/system/system_utils.py
availsim4core/src/context/system/children_logic/__init__.py
availsim4core/src/context/system/children_logic/and_.py
availsim4core/src/context/system/children_logic/children_logic.py
availsim4core/src/context/system/children_logic/children_logic_factory.py
availsim4core/src/context/system/children_logic/oo.py
availsim4-2.2.1.dist-info/METADATA
availsim4-2.2.1.dist-info/WHEEL
availsim4-2.2.1.dist-info/entry_points.txt
availsim4-2.2.1.dist-info/top_level.txt
availsim4-2.2.1.dist-info/RECORD
