Metadata-Version: 2.4
Name: availsim4
Version: 2.2.1
Summary: Availsim4 is a tool to predict reliability and availability of modern particle accelerators and their related systems.
Author-email: TE-MPE <availsim4-developers@cern.ch>
License:                     GNU GENERAL PUBLIC LICENSE
Project-URL: Homepage, https://gitlab.cern.ch/availsim4/availsim4
Project-URL: Issues, https://gitlab.cern.ch/availsim4/availsim4/issues
Classifier: Programming Language :: Python :: 3
Classifier: Operating System :: OS Independent
Classifier: Intended Audience :: Science/Research
Classifier: Intended Audience :: Manufacturing
Classifier: Intended Audience :: Other Audience
Classifier: License :: OSI Approved :: GNU General Public License v3 (GPLv3)
Classifier: Programming Language :: Python
Requires-Python: >=3.7
License-File: LICENSE
License-File: AUTHORS
Requires-Dist: numpy>1.20
Requires-Dist: pandas>2.1
Requires-Dist: datetime
Requires-Dist: openpyxl>3
Requires-Dist: scipy>1.10
Requires-Dist: xlsxwriter>3.1
Provides-Extra: test
Requires-Dist: pytest; extra == "test"
Requires-Dist: memory_profiler; extra == "test"
Requires-Dist: Pillow; extra == "test"
Requires-Dist: pytest-cov; extra == "test"
Provides-Extra: quasi-mc
Requires-Dist: qmcpy==1.6.1; extra == "quasi-mc"
Provides-Extra: graphs
Requires-Dist: matplotlib; extra == "graphs"
Requires-Dist: networkx; extra == "graphs"
Requires-Dist: pygraphviz; extra == "graphs"
Provides-Extra: dev
Requires-Dist: pre-commit; extra == "dev"
Dynamic: license-file
